svg_ultralight/__init__.py
svg_ultralight/animate.py
svg_ultralight/attrib_hints.py
svg_ultralight/bounding_boxes/__init__.py
svg_ultralight/bounding_boxes/bound_helpers.py
svg_ultralight/bounding_boxes/padded_text_initializers.py
svg_ultralight/bounding_boxes/supports_bounds.py
svg_ultralight/bounding_boxes/type_bound_collection.py
svg_ultralight/bounding_boxes/type_bound_element.py
svg_ultralight/bounding_boxes/type_bounding_box.py
svg_ultralight/bounding_boxes/type_padded_list.py
svg_ultralight/bounding_boxes/type_padded_text.py
svg_ultralight/constructors/__init__.py
svg_ultralight/constructors/new_element.py
svg_ultralight/font_tools/__init__.py
svg_ultralight/font_tools/font_info.py
svg_ultralight/image_ops.py
svg_ultralight/inkscape.py
svg_ultralight/layout.py
svg_ultralight/main.py
svg_ultralight/metadata.py
svg_ultralight/nsmap.py
svg_ultralight/py.typed
svg_ultralight/query.py
svg_ultralight/root_elements.py
svg_ultralight/string_conversion.py
svg_ultralight/strings/__init__.py
svg_ultralight/strings/svg_strings.py
svg_ultralight/transformations.py
svg_ultralight/unit_conversion.py
svg_ultralight-0.89.1.dist-info/WHEEL
svg_ultralight-0.89.1.dist-info/METADATA
svg_ultralight-0.89.1.dist-info/RECORD
