Metadata-Version: 2.4
Name: svg-ultralight
Version: 0.89.1
Summary: a sensible way to create svg files with Python
Author: Shay Hill
Author-email: Shay Hill <shay_public@hotmail.com>
License-Expression: MIT
Requires-Dist: cssutils>=2.11.1
Requires-Dist: fonttools>=4.60.1
Requires-Dist: lxml>=6.0.2
Requires-Dist: paragraphs>=1.0.1
Requires-Dist: pillow>=11.3.0
Requires-Dist: svg-path-data>=0.5.3
Requires-Dist: types-lxml>=2025.8.25
Requires-Dist: typing-extensions>=4.15.0
Requires-Python: >=3.10
